ConsoleLog/__init__.py
DBLog/__init__.py
Menu/__init__.py
SendMail/__init__.py
SubscribeValidator/__init__.py
lazy_pink_pants-1.0.1.dist-info/LICENSE
lazy_pink_pants-1.0.1.dist-info/METADATA
lazy_pink_pants-1.0.1.dist-info/WHEEL
lazy_pink_pants-1.0.1.dist-info/top_level.txt
lazy_pink_pants-1.0.1.dist-info/RECORD
